mdhar94_de_toolkit/__init__.py
mdhar94_de_toolkit/main.py
mdhar94_de_toolkit/vm.py
mdhar94_de_toolkit-0.1.1.dist-info/METADATA
mdhar94_de_toolkit-0.1.1.dist-info/WHEEL
mdhar94_de_toolkit-0.1.1.dist-info/entry_points.txt
mdhar94_de_toolkit-0.1.1.dist-info/RECORD
