Metadata-Version: 2.1
Name: mdhar94-de-toolkit
Version: 0.1.1
Summary: 
Author: Mischa Dhar
Author-email: mischadhar94@gmail.com
Requires-Python: >=3.8,<4.0
Classifier: Programming Language :: Python :: 3
Classifier: Programming Language :: Python :: 3.8
Classifier: Programming Language :: Python :: 3.9
Classifier: Programming Language :: Python :: 3.10
Classifier: Programming Language :: Python :: 3.11
Requires-Dist: click (>=8.1.7,<9.0.0)
